osifinanceAPI/__init__.py
osifinanceAPI/osifinance.py
osifinanceAPI/state_taxes.py
osifinanceAPI-0.1.1.dist-info/LICENSE
osifinanceAPI-0.1.1.dist-info/METADATA
osifinanceAPI-0.1.1.dist-info/WHEEL
osifinanceAPI-0.1.1.dist-info/top_level.txt
osifinanceAPI-0.1.1.dist-info/RECORD
