Metadata-Version: 2.1
Name: osifinanceAPI
Version: 0.1.1
Summary: Python toolkit for interacting with the OSI Finance API
Requires-Python: >=3.6
License-File: LICENSE
Requires-Dist: pandas >=1.1.5
